groupdocsassemblycloud/__init__.py
groupdocsassemblycloud/api_client.py
groupdocsassemblycloud/configuration.py
groupdocsassemblycloud/rest.py
groupdocsassemblycloud/apis/__init__.py
groupdocsassemblycloud/apis/assembly_api.py
groupdocsassemblycloud/models/__init__.py
groupdocsassemblycloud/models/api_error.py
groupdocsassemblycloud/models/assemble_options.py
groupdocsassemblycloud/models/assembly_api_error_response.py
groupdocsassemblycloud/models/assembly_response.py
groupdocsassemblycloud/models/error.py
groupdocsassemblycloud/models/error_details.py
groupdocsassemblycloud/models/file_formats_response.py
groupdocsassemblycloud/models/file_response.py
groupdocsassemblycloud/models/files_list.py
groupdocsassemblycloud/models/files_upload_result.py
groupdocsassemblycloud/models/format.py
groupdocsassemblycloud/models/format_collection.py
groupdocsassemblycloud/models/storage_file.py
groupdocsassemblycloud/models/template_file_info.py
groupdocsassemblycloud/models/requests/__init__.py
groupdocsassemblycloud/models/requests/assemble_document_request.py
groupdocsassemblycloud/models/requests/copy_file_request.py
groupdocsassemblycloud/models/requests/copy_folder_request.py
groupdocsassemblycloud/models/requests/create_folder_request.py
groupdocsassemblycloud/models/requests/delete_file_request.py
groupdocsassemblycloud/models/requests/delete_folder_request.py
groupdocsassemblycloud/models/requests/download_file_request.py
groupdocsassemblycloud/models/requests/get_files_list_request.py
groupdocsassemblycloud/models/requests/get_supported_file_formats_request.py
groupdocsassemblycloud/models/requests/move_file_request.py
groupdocsassemblycloud/models/requests/move_folder_request.py
groupdocsassemblycloud/models/requests/upload_file_request.py
test/__init__.py
test/base_test_context.py
test/test_api.py
groupdocs_assembly_cloud-21.1.0.dist-info/METADATA
groupdocs_assembly_cloud-21.1.0.dist-info/WHEEL
groupdocs_assembly_cloud-21.1.0.dist-info/top_level.txt
groupdocs_assembly_cloud-21.1.0.dist-info/RECORD
