Metadata-Version: 2.1
Name: groupdocs-assembly-cloud
Version: 21.1.0
Summary: GroupDocs.Assembly for Cloud API Reference
Home-page: https://github.com/groupdocs-assembly-cloud
Author: Yaroslaw Ekimov
Author-email: yaroslaw.ekimov@aspose.com
License: UNKNOWN
Keywords: groupdocs,python,groupdocs cloud,assembly
Platform: UNKNOWN
Classifier: Development Status :: 5 - Production/Stable
Classifier: Intended Audience :: Developers
Classifier: Topic :: Office/Business :: Office Suites
Classifier: Topic :: Software Development :: Libraries
Classifier: License :: OSI Approved :: MIT License
Classifier: Programming Language :: Python :: 3.4
Classifier: Programming Language :: Python :: 3.5
Classifier: Programming Language :: Python :: 3.6
Requires-Dist: urllib3 (>=1.16)
Requires-Dist: six (>=1.10)
Requires-Dist: certifi
Requires-Dist: python-dateutil
